VerilogFiles/test/tb.v
`timescale 1ns/1ns

module tb;
  reg x=1'b0;
  
  always
    begin
      #10  x=~x;
    end
  
  initial 
    begin
      $dumpfile("dump.vcd");
      $dumpvars(1);
    end
  
  initial
    begin
      #200 $finish;
    end
endmodule

VerilogFiles/test/dump.vcd
$date
	Mon Nov 13 12:12:48 2023
$end
$version
	Icarus Verilog
$end
$timescale
	1ns
$end
$scope module tb $end
$var reg 1 ! x $end
$upscope $end
$enddefinitions $end
#0
$dumpvars
0!
$end
#10
1!
#20
0!
#30
1!
#40
0!
#50
1!
#60
0!
#70
1!
#80
0!
#90
1!
#100
0!
#110
1!
#120
0!
#130
1!
#140
0!
#150
1!
#160
0!
#170
1!
#180
0!
#190
1!
#200
0!
