VerilogFiles/personal/inv.v
module inv(input inp, output oup);
wire w1;
supply1 vdd;
nmos n1 (oup, vdd, inp);
pmos p1 (oup, vdd, inp);
endmodule

VerilogFiles/personal/tb.v
`timescale 10ns/1ns
`include "inv.v"
module tb;

reg in;
wire out;
inv mod0 (in, out);

initial begin
    $monitor("in : %b , out : %b", in, out);
    #10 in = 1'b0;
    #10 in = 1'b1;
    #10 in = 1'b0;
    #10 in = 1'b1;
    #10 in = 1'b0;
    #10 in = 1'b1;
    #10 in = 1'b0;
    #10 in = 1'b1;
    #10 in = 1'b0;
    $finish;
end

initial begin
    $dumpfile("tb.vcd");
    $dumpvars(0, tb);
end

endmodule

VerilogFiles/personal/tb.vcd
$date
	Thu Jan 18 04:32:16 2024
$end
$version
	Icarus Verilog
$end
$timescale
	1ns
$end
$scope module tb $end
$var wire 1 ! out $end
$var reg 1 " in $end
$scope module mod0 $end
$var wire 1 " inp $end
$var wire 1 ! oup $end
$var wire 1 # vdd $end
$upscope $end
$upscope $end
$enddefinitions $end
#0
$dumpvars
1#
x"
x!
$end
#100
1!
0"
#200
1!
1"
#300
0"
#400
1!
1"
#500
0"
#600
1!
1"
#700
0"
#800
1!
1"
#900
0"
